merit/__init__.py
merit/cli.py
merit/utils.py
merit/api/__init__.py
merit/api/base.py
merit/api/errors.py
merit/api/gemini_client.py
merit/api/openai_client.py
merit/api/run_config.py
merit/core/__init__.py
merit/core/cache.py
merit/core/errors.py
merit/core/logging.py
merit/core/models.py
merit/core/prompts.py
merit/core/utils.py
merit/evaluation/__init__.py
merit/evaluation/errors.py
merit/evaluation/evaluators/__init__.py
merit/evaluation/evaluators/base.py
merit/evaluation/evaluators/llm.py
merit/evaluation/evaluators/rag.py
merit/evaluation/templates/__init__.py
merit/knowledge/__init__.py
merit/knowledge/config.py
merit/knowledge/errors.py
merit/knowledge/knowledgebase.py
merit/knowledge/prompts.py
merit/metrics/__init__.py
merit/metrics/base.py
merit/metrics/classification.py
merit/metrics/evaluation.py
merit/metrics/llm_measured.py
merit/metrics/monitoring.py
merit/metrics/prompts.py
merit/metrics/rag.py
merit/monitoring/__init__.py
merit/monitoring/llm.py
merit/monitoring/models.py
merit/monitoring/service.py
merit/monitoring/collectors/__init__.py
merit/monitoring/collectors/api_collector.py
merit/monitoring/collectors/collector.py
merit/monitoring/collectors/java_kafka_adapter.py
merit/monitoring/collectors/kafka_collector.py
merit/monitoring/collectors/log_collector.py
merit/storage/__init__.py
merit/storage/file_storage.py
merit/storage/mongodb_storage.py
merit/storage/persistence.py
merit/templates/__init__.py
merit/templates/demo_features.py
merit/templates/templates.py
merit/testset_generation/__init__.py
merit/testset_generation/analysis.py
merit/testset_generation/errors.py
merit/testset_generation/generator.py
merit/testset_generation/prompts.py
merit/testset_generation/utils.py
merit_ai-0.1.16.dist-info/licenses/LICENSE
merit_ai-0.1.16.dist-info/METADATA
merit_ai-0.1.16.dist-info/WHEEL
merit_ai-0.1.16.dist-info/entry_points.txt
merit_ai-0.1.16.dist-info/top_level.txt
merit_ai-0.1.16.dist-info/RECORD
