Metadata-Version: 2.4
Name: merit-ai
Version: 0.1.16
Summary: Monitoring, Evaluation, Reporting, Inspection, Testing framework for AI systems
Author: adithyakpb
License: MIT License
Classifier: Development Status :: 3 - Alpha
Classifier: Intended Audience :: Developers
Classifier: Intended Audience :: Science/Research
Classifier: License :: OSI Approved :: MIT License
Classifier: Programming Language :: Python :: 3
Classifier: Programming Language :: Python :: 3.8
Classifier: Programming Language :: Python :: 3.9
Classifier: Programming Language :: Python :: 3.10
Classifier: Programming Language :: Python :: 3.11
Classifier: Topic :: Scientific/Engineering :: Artificial Intelligence
Requires-Python: >=3.8
License-File: LICENSE
Requires-Dist: pydantic
Requires-Dist: openai>=1.0.0
Requires-Dist: click>=8.1.3
Requires-Dist: requests
Requires-Dist: python-dotenv
Requires-Dist: jsonschema
Provides-Extra: openai
Requires-Dist: openai>=1.0.0; extra == "openai"
Provides-Extra: google
Requires-Dist: google-generativeai>=0.3.0; extra == "google"
Provides-Extra: analysis
Requires-Dist: numpy; extra == "analysis"
Requires-Dist: scikit-learn; extra == "analysis"
Requires-Dist: umap-learn; extra == "analysis"
Requires-Dist: hdbscan; extra == "analysis"
Requires-Dist: pymongo>=4.0; extra == "analysis"
Provides-Extra: dev
Requires-Dist: pytest>=7.3.1; extra == "dev"
Requires-Dist: pytest-cov>=4.1.0; extra == "dev"
Requires-Dist: pytest-mock>=3.10.0; extra == "dev"
Requires-Dist: pytest-xdist>=3.3.1; extra == "dev"
Requires-Dist: pytest-rerunfailures>=11.1.2; extra == "dev"
Requires-Dist: responses>=0.23.1; extra == "dev"
Requires-Dist: black>=23.3.0; extra == "dev"
Requires-Dist: isort>=5.12.0; extra == "dev"
Requires-Dist: flake8>=6.0.0; extra == "dev"
Requires-Dist: mypy>=1.3.0; extra == "dev"
Requires-Dist: tox>=4.6.3; extra == "dev"
Provides-Extra: docs
Requires-Dist: sphinx>=7.0.1; extra == "docs"
Requires-Dist: sphinx-rtd-theme>=1.2.2; extra == "docs"
Requires-Dist: sphinx-autodoc-typehints>=1.23.0; extra == "docs"
Provides-Extra: all
Requires-Dist: merit[analysis,dev,docs,google,openai]; extra == "all"
Dynamic: license-file
